Metadata-Version: 1.1
Name: openvas-lib
Version: 1.1.5
Summary: OpenVAS Manager for OpenVAS 6 to 8 and XML report parser
Home-page: http://www.golismero.com/
Author: Daniel Garcia Garcia (cr0hn)
Author-email: cr0hn@cr0hn.com
License: BSD3
Download-URL: https://github.com/golismero/openvas_lib/zipball/master
Platform: UNKNOWN
Classifier: Development Status :: 4 - Beta
Classifier: Intended Audience :: Developers
Classifier: Intended Audience :: Information Technology
Classifier: License :: OSI Approved :: GNU General Public License v2 (GPLv2)
Classifier: Natural Language :: English
Classifier: Operating System :: MacOS :: MacOS X
Classifier: Operating System :: Microsoft :: Windows
Classifier: Operating System :: POSIX
Classifier: Operating System :: POSIX :: BSD :: FreeBSD
Classifier: Operating System :: POSIX :: Linux
Classifier: Operating System :: Unix
Classifier: Programming Language :: Python :: 2.7
Classifier: Programming Language :: Python :: 3
Classifier: Topic :: Security
